neural_wrappers/__init__.py
neural_wrappers/callbacks/__init__.py
neural_wrappers/callbacks/callback.py
neural_wrappers/callbacks/callback_name.py
neural_wrappers/callbacks/confusion_matrix.py
neural_wrappers/callbacks/early_stopping.py
neural_wrappers/callbacks/metric_thresholder.py
neural_wrappers/callbacks/metric_with_threshold_wrapper.py
neural_wrappers/callbacks/plot_metrics.py
neural_wrappers/callbacks/precision_recall_curve.py
neural_wrappers/callbacks/save_history.py
neural_wrappers/callbacks/save_models.py
neural_wrappers/callbacks/save_models_self_supervised.py
neural_wrappers/graph/__init__.py
neural_wrappers/graph/draw_graph.py
neural_wrappers/graph/edge.py
neural_wrappers/graph/graph.py
neural_wrappers/graph/graph_serializer.py
neural_wrappers/graph/node.py
neural_wrappers/graph/utils/__init__.py
neural_wrappers/graph/utils/concatenate.py
neural_wrappers/graph/utils/edge_utils.py
neural_wrappers/graph/utils/forward_messages.py
neural_wrappers/graph/utils/reduce.py
neural_wrappers/graph_stable/__init__.py
neural_wrappers/graph_stable/draw_graph.py
neural_wrappers/graph_stable/edge.py
neural_wrappers/graph_stable/graph.py
neural_wrappers/graph_stable/graph_serializer.py
neural_wrappers/graph_stable/node.py
neural_wrappers/graph_stable/utils/__init__.py
neural_wrappers/graph_stable/utils/concatenate.py
neural_wrappers/graph_stable/utils/edge_utils.py
neural_wrappers/graph_stable/utils/forward_messages.py
neural_wrappers/graph_stable/utils/line_printer.py
neural_wrappers/graph_stable/utils/reduce.py
neural_wrappers/metrics/__init__.py
neural_wrappers/metrics/accuracy.py
neural_wrappers/metrics/f1score.py
neural_wrappers/metrics/inter_class_accuracy.py
neural_wrappers/metrics/mean_iou.py
neural_wrappers/metrics/metric.py
neural_wrappers/metrics/metric_with_threshold.py
neural_wrappers/metrics/metric_wrapper.py
neural_wrappers/metrics/precision.py
neural_wrappers/metrics/precision_recall.py
neural_wrappers/metrics/recall.py
neural_wrappers/models/__init__.py
neural_wrappers-0.31.dist-info/LICENSE.TXT
neural_wrappers-0.31.dist-info/METADATA
neural_wrappers-0.31.dist-info/WHEEL
neural_wrappers-0.31.dist-info/top_level.txt
neural_wrappers-0.31.dist-info/RECORD
