Metadata-Version: 2.1
Name: neural-wrappers
Version: 0.31
Summary: Generic PyTorch high level wrapper
Home-page: https://gitlab.com/mihaicristianpirvu/neural-wrappers
Author: Mihai Cristian Pîrvu
Author-email: mihaicristianpirvu@gmail.com
License: WTFPL
Keywords: PyTorch,neural network,high level api
Platform: UNKNOWN
Classifier: Programming Language :: Python :: 3
Classifier: Operating System :: OS Independent
Requires-Python: >=3.8
Requires-Dist: matplotlib
Requires-Dist: tqdm
Requires-Dist: opencv-python
Requires-Dist: lycon
Requires-Dist: h5py
Requires-Dist: overrides
Requires-Dist: scikit-learn
Requires-Dist: graphviz
Requires-Dist: transforms3d
Requires-Dist: prefetch-generator
Requires-Dist: returns
Requires-Dist: pims
